archimedes/__init__.py
archimedes/discretize.py
archimedes/error.py
archimedes/py.typed
archimedes/theme.py
archimedes/typing.py
archimedes/_core/__init__.py
archimedes/_core/_array_impl.py
archimedes/_core/_autodiff.py
archimedes/_core/_interpolant.py
archimedes/_core/_type_inference.py
archimedes/_core/utils.py
archimedes/_core/_array_ops/__init__.py
archimedes/_core/_array_ops/_array_function.py
archimedes/_core/_array_ops/_array_ops.py
archimedes/_core/_array_ops/_array_ufunc.py
archimedes/_core/_codegen/__init__.py
archimedes/_core/_codegen/_codegen.py
archimedes/_core/_codegen/_renderer.py
archimedes/_core/_codegen/_templates/arduino.j2
archimedes/_core/_codegen/_templates/c_api.c.j2
archimedes/_core/_codegen/_templates/c_api.h.j2
archimedes/_core/_codegen/_templates/c_application.j2
archimedes/_core/_function/__init__.py
archimedes/_core/_function/_callback.py
archimedes/_core/_function/_compile.py
archimedes/_core/_function/_control_flow.py
archimedes/docs/__init__.py
archimedes/docs/utils.py
archimedes/experimental/README.md
archimedes/experimental/__init__.py
archimedes/experimental/balanced_truncation.py
archimedes/experimental/events.py
archimedes/experimental/lqr.py
archimedes/experimental/nlhw.py
archimedes/experimental/aero/__init__.py
archimedes/experimental/aero/atmosphere.py
archimedes/experimental/aero/frames.py
archimedes/experimental/aero/gravity.py
archimedes/experimental/aero/sensors.py
archimedes/experimental/astro/__init__.py
archimedes/experimental/astro/constants.py
archimedes/experimental/astro/orbital_elements.py
archimedes/experimental/coco/__init__.py
archimedes/experimental/coco/discretization.py
archimedes/experimental/coco/interpolation.py
archimedes/experimental/coco/mesh_refinement.py
archimedes/experimental/coco/ocp.py
archimedes/experimental/nn/__init__.py
archimedes/experimental/nn/nn.py
archimedes/experimental/observers/__init__.py
archimedes/experimental/observers/_continuous_ekf.py
archimedes/experimental/signal/__init__.py
archimedes-0.4.2.dist-info/METADATA
archimedes-0.4.2.dist-info/WHEEL
archimedes-0.4.2.dist-info/licenses/LICENSE
archimedes-0.4.2.dist-info/RECORD
