Metadata-Version: 2.4
Name: archimedes
Version: 0.4.2
Summary: Python framework for modeling, simulation, and controls development
Project-URL: Source, https://github.com/pinetreelabs/archimedes/
Project-URL: Documentation, https://pinetreelabs.github.io/archimedes/
Project-URL: Issues, https://github.com/pinetreelabs/archimedes/issues
Author-email: Jared Callaham <jared.callaham@gmail.com>
License-Expression: GPL-3.0-or-later
License-File: LICENSE
Requires-Python: >=3.11
Requires-Dist: casadi>=3.6.7
Requires-Dist: jinja2>=3.1.6
Requires-Dist: numpy>=2.2.4
Requires-Dist: osqp>=1.0.4
Requires-Dist: pydantic>=2.11.9
Requires-Dist: scipy>=1.15.2
Requires-Dist: typing-extensions>=4.12.2
Provides-Extra: all
Requires-Dist: control>=0.10.1; extra == 'all'
Requires-Dist: ipykernel>=6.29.5; extra == 'all'
Requires-Dist: jupyter>=1.1.1; extra == 'all'
Requires-Dist: matplotlib>=3.10.1; extra == 'all'
